{
  "name": "report_analysis",
  "description": "Report the tone, clarity, and professionalism analysis of the reviewed message. Always call this tool with the complete structured result.",
  "input_schema": {
    "type": "object",
    "additionalProperties": true,
    "required": [
      "flagged"
    ],
    "properties": {
      "flagged": {
        "type": "boolean"
      },
      "confidence": {
        "type": "number",
        "minimum": 0,
        "maximum": 1
      },
      "mode": {
        "type": "string",
        "enum": [
          "",
          "tone",
          "polish",
          "both"
        ]
      },
      "readability": {
        "type": "number",
        "minimum": 0,
        "maximum": 16
      },
      "red_flags": {
        "type": "array",
        "items": {
          "type": "string"
        }
      },
      "categories": {
        "type": "array",
        "items": {
          "type": "string",
          "enum": [
            "adverbs",
            "passive voice",
            "wordy",
            "hedging",
            "hard to read",
            "tone",
            "grammar",
            "clarity",
            "inclusive language",
            "professionalism",
            "structure",
            "audience"
          ]
        }
      },
      "reasoning": {
        "type": "string"
      },
      "suggestion": {
        "type": "string"
      },
      "has_questions": {
        "type": "boolean"
      },
      "questions": {
        "type": "array",
        "maxItems": 3,
        "items": {
          "type": "string"
        }
      },
    }
  }
}
